trendfetcher/__init__.py
trendfetcher/main.py
trendfetcher-0.1.0.dist-info/licenses/LICENSE
trendfetcher-0.1.0.dist-info/METADATA
trendfetcher-0.1.0.dist-info/WHEEL
trendfetcher-0.1.0.dist-info/top_level.txt
trendfetcher-0.1.0.dist-info/RECORD
