Metadata-Version: 2.4
Name: trendfetcher
Version: 0.1.0
Summary: A utility for fetching and rate-limiting Google Trends data via pytrends.
License: MIT
Requires-Python: >=3.9
License-File: LICENSE
Requires-Dist: pytrends>=4.9.2
Requires-Dist: pandas>=2.0.0
Requires-Dist: numpy>=1.25.0
Dynamic: license-file
